collibra_catalog_cloud_ingestions/__init__.py
collibra_catalog_cloud_ingestions/api_client.py
collibra_catalog_cloud_ingestions/configuration.py
collibra_catalog_cloud_ingestions/rest.py
collibra_catalog_cloud_ingestions/api/__init__.py
collibra_catalog_cloud_ingestions/api/adls_api.py
collibra_catalog_cloud_ingestions/api/gcs_api.py
collibra_catalog_cloud_ingestions/api/generic_api.py
collibra_catalog_cloud_ingestions/api/powerbi_api.py
collibra_catalog_cloud_ingestions/api/s3_api.py
collibra_catalog_cloud_ingestions/api/tableau_api.py
collibra_catalog_cloud_ingestions/models/__init__.py
collibra_catalog_cloud_ingestions/models/add_crawler_request.py
collibra_catalog_cloud_ingestions/models/add_file_system_schedule_request.py
collibra_catalog_cloud_ingestions/models/add_generic_schedule_request.py
collibra_catalog_cloud_ingestions/models/change_file_system_schedule_request.py
collibra_catalog_cloud_ingestions/models/change_generic_schedule_request.py
collibra_catalog_cloud_ingestions/models/crawler.py
collibra_catalog_cloud_ingestions/models/crawler_include_path.py
collibra_catalog_cloud_ingestions/models/crawler_include_path_request.py
collibra_catalog_cloud_ingestions/models/generic_configuration.py
collibra_catalog_cloud_ingestions/models/job.py
collibra_catalog_cloud_ingestions/models/remove_crawler_request.py
collibra_catalog_cloud_ingestions/models/save_generic_config_request.py
collibra_catalog_cloud_ingestions/models/schedule.py
collibra_catalog_cloud_ingestions/models/update_crawler_custom_classifiers_request.py
collibra_catalog_cloud_ingestions/models/update_crawler_request.py
test/__init__.py
test/test_add_crawler_request.py
test/test_add_file_system_schedule_request.py
test/test_add_generic_schedule_request.py
test/test_adls_api.py
test/test_change_file_system_schedule_request.py
test/test_change_generic_schedule_request.py
test/test_crawler.py
test/test_crawler_include_path.py
test/test_crawler_include_path_request.py
test/test_gcs_api.py
collibra_catalog_cloud_ingestions_100-1.0.0.dist-info/METADATA
collibra_catalog_cloud_ingestions_100-1.0.0.dist-info/WHEEL
collibra_catalog_cloud_ingestions_100-1.0.0.dist-info/top_level.txt
collibra_catalog_cloud_ingestions_100-1.0.0.dist-info/RECORD
